{
  "accentColor": "{{appsmith.theme.colors.primaryColor}}",
  "animateLoading": true,
  "backgroundColor": "#FFFFFF",
  "borderColor": "#ffffff",
  "borderRadius": "{{appsmith.theme.borderRadius.appBorderRadius}}",
  "borderWidth": 1,
  "bottomRow": 81,
  "boxShadow": "none",
  "children": [
    {
      "borderRadius": "{{appsmith.theme.borderRadius.appBorderRadius}}",
      "bottomRow": 630,
      "boxShadow": "{{appsmith.theme.boxShadow.appBoxShadow}}",
      "canExtend": true,
      "detachFromLayout": true,
      "dynamicBindingPathList": [
        {
          "key": "borderRadius"
        },
        {
          "key": "boxShadow"
        }
      ],
      "dynamicHeight": "AUTO_HEIGHT",
      "dynamicTriggerPathList": [],
      "flexLayers": [],
      "isDisabled": false,
      "isLoading": false,
      "isVisible": true,
      "key": "rya47o977t",
      "leftColumn": 0,
      "maxDynamicHeight": 9000,
      "minDynamicHeight": 4,
      "minHeight": 150,
      "minWidth": 450,
      "mobileBottomRow": 150,
      "mobileLeftColumn": 0,
      "mobileRightColumn": 141.53125,
      "mobileTopRow": 0,
      "needsErrorInfo": false,
      "parentColumnSpace": 1,
      "parentId": "l9emmtqxr3",
      "parentRowSpace": 1,
      "renderMode": "CANVAS",
      "responsiveBehavior": "fill",
      "rightColumn": 141.53125,
      "shouldScrollContents": false,
      "tabId": "tab1",
      "tabName": "User Management",
      "topRow": 0,
      "type": "CANVAS_WIDGET",
      "version": 1,
      "widgetId": "w3ag1nusfu",
      "widgetName": "Canvas7"
    },
    {
      "borderRadius": "{{appsmith.theme.borderRadius.appBorderRadius}}",
      "bottomRow": 630,
      "boxShadow": "{{appsmith.theme.boxShadow.appBoxShadow}}",
      "canExtend": true,
      "detachFromLayout": true,
      "dynamicBindingPathList": [
        {
          "key": "borderRadius"
        },
        {
          "key": "boxShadow"
        }
      ],
      "dynamicHeight": "AUTO_HEIGHT",
      "dynamicTriggerPathList": [],
      "flexLayers": [],
      "isDisabled": false,
      "isLoading": false,
      "isVisible": true,
      "key": "rya47o977t",
      "leftColumn": 0,
      "maxDynamicHeight": 9000,
      "minDynamicHeight": 4,
      "minHeight": 150,
      "minWidth": 450,
      "mobileBottomRow": 150,
      "mobileLeftColumn": 0,
      "mobileRightColumn": 141.53125,
      "mobileTopRow": 0,
      "needsErrorInfo": false,
      "parentColumnSpace": 1,
      "parentId": "l9emmtqxr3",
      "parentRowSpace": 1,
      "renderMode": "CANVAS",
      "responsiveBehavior": "fill",
      "rightColumn": 141.53125,
      "shouldScrollContents": false,
      "tabId": "tab2",
      "tabName": "Beach Info",
      "topRow": 0,
      "type": "CANVAS_WIDGET",
      "version": 1,
      "widgetId": "w4eelemfg0",
      "widgetName": "Canvas8"
    },
    {
      "borderRadius": "{{appsmith.theme.borderRadius.appBorderRadius}}",
      "bottomRow": 630,
      "boxShadow": "{{appsmith.theme.boxShadow.appBoxShadow}}",
      "canExtend": false,
      "containerStyle": "none",
      "detachFromLayout": true,
      "dynamicBindingPathList": [
        {
          "key": "borderRadius"
        },
        {
          "key": "boxShadow"
        }
      ],
      "dynamicHeight": "AUTO_HEIGHT",
      "dynamicTriggerPathList": [],
      "flexLayers": [],
      "isLoading": false,
      "isVisible": true,
      "key": "rya47o977t",
      "leftColumn": 0,
      "maxDynamicHeight": 9000,
      "minDynamicHeight": 4,
      "minHeight": 840,
      "minWidth": 450,
      "mobileBottomRow": 841,
      "mobileLeftColumn": 0,
      "mobileRightColumn": 1253.5625,
      "mobileTopRow": 1,
      "needsErrorInfo": false,
      "parentColumnSpace": 1,
      "parentId": "l9emmtqxr3",
      "parentRowSpace": 1,
      "renderMode": "CANVAS",
      "responsiveBehavior": "fill",
      "rightColumn": 1253.5625,
      "tabId": "tabbtm4bgkiox",
      "tabName": "Announcements",
      "topRow": 1,
      "type": "CANVAS_WIDGET",
      "version": 1,
      "widgetId": "2zem1rvo9x",
      "widgetName": "Canvas9"
    }
  ],
  "defaultTab": "{{util_func.defaultTab}}",
  "dynamicBindingPathList": [
    {
      "key": "accentColor"
    },
    {
      "key": "borderRadius"
    },
    {
      "key": "defaultTab"
    }
  ],
  "dynamicHeight": "AUTO_HEIGHT",
  "dynamicTriggerPathList": [],
  "flexVerticalAlignment": "stretch",
  "isCanvas": true,
  "isLoading": false,
  "isVisible": true,
  "key": "4kkizyz0m9",
  "leftColumn": 10,
  "maxDynamicHeight": 9000,
  "minDynamicHeight": 10,
  "minWidth": 450,
  "mobileBottomRow": 33,
  "mobileLeftColumn": 0,
  "mobileRightColumn": 7,
  "mobileTopRow": 18,
  "needsErrorInfo": false,
  "originalBottomRow": 81,
  "originalTopRow": 18,
  "parentColumnSpace": 20.21875,
  "parentId": "0",
  "parentRowSpace": 10,
  "renderMode": "CANVAS",
  "responsiveBehavior": "fill",
  "rightColumn": 63,
  "shouldScrollContents": true,
  "shouldShowTabs": false,
  "tabsObj": {
    "tab1": {
      "id": "tab1",
      "index": 2,
      "isDuplicateLabel": false,
      "isVisible": true,
      "label": "User Management",
      "positioning": "vertical",
      "widgetId": "w3ag1nusfu"
    },
    "tab2": {
      "id": "tab2",
      "index": 1,
      "isDuplicateLabel": false,
      "isVisible": true,
      "label": "Beach Info",
      "positioning": "vertical",
      "widgetId": "w4eelemfg0"
    },
    "tabbtm4bgkiox": {
      "id": "tabbtm4bgkiox",
      "index": 0,
      "isDuplicateLabel": false,
      "isVisible": true,
      "label": "Announcements",
      "widgetId": "2zem1rvo9x"
    }
  },
  "topRow": 18,
  "type": "TABS_WIDGET",
  "version": 3,
  "widgetId": "l9emmtqxr3",
  "widgetName": "Tabs1"
}